dftopo/__init__.py
dftopo/dfps.py
dftopo-1.0.6.dist-info/LICENSE
dftopo-1.0.6.dist-info/METADATA
dftopo-1.0.6.dist-info/WHEEL
dftopo-1.0.6.dist-info/top_level.txt
dftopo-1.0.6.dist-info/RECORD
