Metadata-Version: 2.1
Name: dftopo
Version: 1.0.6
Summary: Pass postgres data to pandas dataframe
Home-page: https://github.com/joigmz/dataframe_to_postgres
Author: Jose Izam
Author-email: jose.izam99@gmail.com
License: UNKNOWN
Project-URL: Bug Tracker, https://github.com/joigmz/dataframe_to_postgres
Platform: UNKNOWN
Classifier: Programming Language :: Python :: 3
Classifier: License :: OSI Approved :: MIT License
Classifier: Operating System :: OS Independent
Requires-Python: >=3.6
License-File: LICENSE
Requires-Dist: pandas
Requires-Dist: sqlalchemy
